<featureType>
  <id>FeatureTypeInfoImpl--5aa50211:17a007a58ce:-7fdf</id>
  <name>bmv_meetpunten_(grondwater)</name>
  <nativeName>bmv_meetpunten_(grondwater)</nativeName>
  <namespace>
    <id>NamespaceInfoImpl--5aa50211:17a007a58ce:-7fed</id>
  </namespace>
  <title>BMV_meetpunten_(grondwater)</title>
  <keywords>
    <string>features</string>
    <string>bmv_meetpunten_(grondwater)</string>
  </keywords>
  <nativeCRS class="projected">PROJCS[&quot;Amersfoort / RD New&quot;, 
  GEOGCS[&quot;Amersfoort&quot;, 
    DATUM[&quot;Amersfoort&quot;, 
      SPHEROID[&quot;Bessel 1841&quot;, 6377397.155, 299.1528128, AUTHORITY[&quot;EPSG&quot;,&quot;7004&quot;]], 
      TOWGS84[565.2369, 50.0087, 465.658, -0.40685733032239757, -0.3507326765425626, 1.8703473836067956, 4.0812], 
      AUTHORITY[&quot;EPSG&quot;,&quot;6289&quot;]], 
    PRIMEM[&quot;Greenwich&quot;, 0.0, AUTHORITY[&quot;EPSG&quot;,&quot;8901&quot;]], 
    UNIT[&quot;degree&quot;, 0.017453292519943295], 
    AXIS[&quot;Geodetic longitude&quot;, EAST], 
    AXIS[&quot;Geodetic latitude&quot;, NORTH], 
    AUTHORITY[&quot;EPSG&quot;,&quot;4289&quot;]], 
  PROJECTION[&quot;Oblique_Stereographic&quot;], 
  PARAMETER[&quot;central_meridian&quot;, 5.387638888888891], 
  PARAMETER[&quot;latitude_of_origin&quot;, 52.15616055555556], 
  PARAMETER[&quot;scale_factor&quot;, 0.9999079], 
  PARAMETER[&quot;false_easting&quot;, 155000.0], 
  PARAMETER[&quot;false_northing&quot;, 463000.0], 
  UNIT[&quot;m&quot;, 1.0], 
  AXIS[&quot;Easting&quot;, EAST], 
  AXIS[&quot;Northing&quot;, NORTH], 
  AUTHORITY[&quot;EPSG&quot;,&quot;28992&quot;]]</nativeCRS>
  <srs>EPSG:28992</srs>
  <nativeBoundingBox>
    <minx>137455.0</minx>
    <maxx>152142.0</maxx>
    <miny>394074.0</miny>
    <maxy>405276.0</maxy>
  </nativeBoundingBox>
  <latLonBoundingBox>
    <minx>5.133766308884753</minx>
    <maxx>5.346009190024304</maxx>
    <miny>51.535370424192394</miny>
    <maxy>51.63632657384154</maxy>
    <crs>EPSG:4326</crs>
  </latLonBoundingBox>
  <projectionPolicy>FORCE_DECLARED</projectionPolicy>
  <enabled>true</enabled>
  <advertised>true</advertised>
  <store class="dataStore">
    <id>DataStoreInfoImpl--5aa50211:17a007a58ce:-7fe0</id>
  </store>
  <serviceConfiguration>false</serviceConfiguration>
  <simpleConversionEnabled>false</simpleConversionEnabled>
  <maxFeatures>0</maxFeatures>
  <numDecimals>0</numDecimals>
  <padWithZeros>false</padWithZeros>
  <forcedDecimal>false</forcedDecimal>
  <attributes>
    <attribute>
      <name>geom</name>
      <minOccurs>0</minOccurs>
      <maxOccurs>1</maxOccurs>
      <nillable>true</nillable>
      <binding>org.locationtech.jts.geom.Point</binding>
    </attribute>
    <attribute>
      <name>GEBIED</name>
      <minOccurs>0</minOccurs>
      <maxOccurs>1</maxOccurs>
      <nillable>true</nillable>
      <binding>java.lang.String</binding>
    </attribute>
    <attribute>
      <name>MEETPUNT__</name>
      <minOccurs>0</minOccurs>
      <maxOccurs>1</maxOccurs>
      <nillable>true</nillable>
      <binding>java.lang.String</binding>
    </attribute>
    <attribute>
      <name>TOEST____V</name>
      <minOccurs>0</minOccurs>
      <maxOccurs>1</maxOccurs>
      <nillable>true</nillable>
      <binding>java.lang.String</binding>
    </attribute>
    <attribute>
      <name>P_PEILBUIS</name>
      <minOccurs>0</minOccurs>
      <maxOccurs>1</maxOccurs>
      <nillable>true</nillable>
      <binding>java.lang.String</binding>
    </attribute>
    <attribute>
      <name>TNO_NR</name>
      <minOccurs>0</minOccurs>
      <maxOccurs>1</maxOccurs>
      <nillable>true</nillable>
      <binding>java.lang.String</binding>
    </attribute>
    <attribute>
      <name>OLGA_NR</name>
      <minOccurs>0</minOccurs>
      <maxOccurs>1</maxOccurs>
      <nillable>true</nillable>
      <binding>java.lang.String</binding>
    </attribute>
    <attribute>
      <name>DATUM_INRI</name>
      <minOccurs>0</minOccurs>
      <maxOccurs>1</maxOccurs>
      <nillable>true</nillable>
      <binding>java.sql.Date</binding>
    </attribute>
    <attribute>
      <name>AANPASSING</name>
      <minOccurs>0</minOccurs>
      <maxOccurs>1</maxOccurs>
      <nillable>true</nillable>
      <binding>java.sql.Date</binding>
    </attribute>
    <attribute>
      <name>D___INZET_</name>
      <minOccurs>0</minOccurs>
      <maxOccurs>1</maxOccurs>
      <nillable>true</nillable>
      <binding>java.lang.String</binding>
    </attribute>
    <attribute>
      <name>EIGENAAR</name>
      <minOccurs>0</minOccurs>
      <maxOccurs>1</maxOccurs>
      <nillable>true</nillable>
      <binding>java.lang.String</binding>
    </attribute>
    <attribute>
      <name>BEHEERDER</name>
      <minOccurs>0</minOccurs>
      <maxOccurs>1</maxOccurs>
      <nillable>true</nillable>
      <binding>java.lang.String</binding>
    </attribute>
    <attribute>
      <name>WAARNEMER</name>
      <minOccurs>0</minOccurs>
      <maxOccurs>1</maxOccurs>
      <nillable>true</nillable>
      <binding>java.lang.String</binding>
    </attribute>
    <attribute>
      <name>X_COORD_IN</name>
      <minOccurs>0</minOccurs>
      <maxOccurs>1</maxOccurs>
      <nillable>true</nillable>
      <binding>java.lang.Integer</binding>
    </attribute>
    <attribute>
      <name>Y_COORD_IN</name>
      <minOccurs>0</minOccurs>
      <maxOccurs>1</maxOccurs>
      <nillable>true</nillable>
      <binding>java.lang.Integer</binding>
    </attribute>
    <attribute>
      <name>BKB_T_O_V_</name>
      <minOccurs>0</minOccurs>
      <maxOccurs>1</maxOccurs>
      <nillable>true</nillable>
      <binding>java.lang.Double</binding>
    </attribute>
    <attribute>
      <name>MV_T_O_V__</name>
      <minOccurs>0</minOccurs>
      <maxOccurs>1</maxOccurs>
      <nillable>true</nillable>
      <binding>java.lang.Double</binding>
    </attribute>
    <attribute>
      <name>BK__FIL__T</name>
      <minOccurs>0</minOccurs>
      <maxOccurs>1</maxOccurs>
      <nillable>true</nillable>
      <binding>java.lang.Double</binding>
    </attribute>
    <attribute>
      <name>OK__FIL__T</name>
      <minOccurs>0</minOccurs>
      <maxOccurs>1</maxOccurs>
      <nillable>true</nillable>
      <binding>java.lang.Double</binding>
    </attribute>
    <attribute>
      <name>DINO_OPGEN</name>
      <minOccurs>0</minOccurs>
      <maxOccurs>1</maxOccurs>
      <nillable>true</nillable>
      <binding>java.lang.String</binding>
    </attribute>
    <attribute>
      <name>BUITEN_GEB</name>
      <minOccurs>0</minOccurs>
      <maxOccurs>1</maxOccurs>
      <nillable>true</nillable>
      <binding>java.lang.String</binding>
    </attribute>
    <attribute>
      <name>GEGEVENS_I</name>
      <minOccurs>0</minOccurs>
      <maxOccurs>1</maxOccurs>
      <nillable>true</nillable>
      <binding>java.lang.String</binding>
    </attribute>
    <attribute>
      <name>ACTIE_VOOR</name>
      <minOccurs>0</minOccurs>
      <maxOccurs>1</maxOccurs>
      <nillable>true</nillable>
      <binding>java.lang.String</binding>
    </attribute>
    <attribute>
      <name>OPMERKINGE</name>
      <minOccurs>0</minOccurs>
      <maxOccurs>1</maxOccurs>
      <nillable>true</nillable>
      <binding>java.lang.String</binding>
    </attribute>
  </attributes>
  <overridingServiceSRS>false</overridingServiceSRS>
  <skipNumberMatched>false</skipNumberMatched>
  <circularArcPresent>false</circularArcPresent>
  <encodeMeasures>false</encodeMeasures>
</featureType>